{
  "seo": {
    "title": "YouTube Shorts Downloader – Tải Shorts Miễn Phí | CONVERT1S",
    "description": "Tải YouTube Shorts với CONVERT1S. Trình tải YouTube Shorts miễn phí lưu Shorts thành MP4 chất lượng HD. Không cần đăng ký hay ứng dụng.",
    "schemaName": "CONVERT1S - YouTube Shorts Downloader",
    "schemaDescription": "CONVERT1S là trình tải YouTube Shorts miễn phí cho phép người dùng lưu YouTube Shorts thành MP4 chất lượng HD.",
    "ogTitle": "YouTube Shorts Downloader – Tải Shorts Miễn Phí | CONVERT1S",
    "ogDescription": "Tải YouTube Shorts bằng CONVERT1S. Miễn phí, nhanh và chất lượng HD."
  },
  "content": {
    "form": {
      "h1": "CONVERT1S – YouTube Shorts Downloader",
      "placeholder": "Dán URL YouTube Shorts vào đây...",
      "button": "Tải Shorts"
    },
    "sections": [
      {
        "h2": "CONVERT1S YouTube Shorts Downloader Là Gì?",
        "p": [
          "CONVERT1S là trình <strong>tải YouTube Shorts</strong> miễn phí cho phép bạn lưu video YouTube Shorts về thiết bị ở định dạng MP4.",
          "Chỉ cần dán link YouTube Shorts, nhấn tải xuống và lưu video chất lượng HD trực tiếp vào điện thoại hoặc máy tính.",
          "Công cụ <strong>YouTube Shorts sang MP4</strong> này hoạt động trên mọi thiết bị và browser mà không cần cài đặt ứng dụng."
        ]
      },
      {
        "h2": "Cách Tải YouTube Shorts",
        "ol": [
          {
            "h3": "Sao Chép Link YouTube Shorts",
            "p": [
              "Mở YouTube và nhấn nút Chia sẻ trên video Shorts muốn tải, sau đó chọn Sao chép liên kết."
            ]
          },
          {
            "h3": "Dán Link",
            "p": [
              "Dán URL YouTube Shorts vào trình tải YouTube Shorts CONVERT1S ở trên."
            ]
          },
          {
            "h3": "Tải Video Shorts",
            "p": [
              "Nhấn nút tải xuống và lưu video YouTube Shorts về thiết bị ở định dạng MP4."
            ]
          }
        ]
      },
      {
        "h2": "Lưu YouTube Shorts Chất Lượng HD",
        "p": [
          "CONVERT1S cho phép bạn <strong>tải YouTube Shorts</strong> ở chất lượng cao nhất hiện có, lên đến độ phân giải Full HD.",
          "Lưu YouTube Shorts yêu thích để xem offline, chia sẻ trên nền tảng khác hoặc thêm vào bộ sưu tập video của bạn."
        ]
      },
      {
        "h2": "Tại Sao Nên Dùng CONVERT1S YouTube Shorts Downloader?",
        "ul": [
          {
            "h3": "Chất Lượng HD",
            "p": [
              "Lưu YouTube Shorts ở chất lượng cao nhất hiện có bao gồm độ phân giải Full HD."
            ]
          },
          {
            "h3": "Tải Nhanh",
            "p": [
              "Tải YouTube Shorts tức thì với máy chủ được tối ưu hóa cho tốc độ tối đa."
            ]
          },
          {
            "h3": "Miễn Phí và Không Giới Hạn",
            "p": [
              "Tải bao nhiêu YouTube Shorts tùy thích hoàn toàn miễn phí, không giới hạn hàng ngày."
            ]
          },
          {
            "h3": "Không Cần Ứng Dụng",
            "p": [
              "Trình tải YouTube Shorts hoạt động trực tiếp trong browser trên mọi thiết bị mà không cần cài ứng dụng."
            ]
          }
        ]
      },
      {
        "h2": "Câu Hỏi Thường Gặp",
        "ul": [
          {
            "h3": "CONVERT1S YouTube Shorts downloader có miễn phí không?",
            "p": [
              "Có. CONVERT1S là trình tải YouTube Shorts hoàn toàn miễn phí, không có phí ẩn."
            ]
          },
          {
            "h3": "Tôi có thể tải YouTube Shorts thành MP4 không?",
            "p": [
              "Có. CONVERT1S lưu YouTube Shorts trực tiếp dưới dạng file MP4 phát được trên mọi thiết bị."
            ]
          },
          {
            "h3": "Có hoạt động trên iPhone và Android không?",
            "p": [
              "Có. Trình tải YouTube Shorts hoạt động trên mọi thiết bị di động và browser máy tính."
            ]
          },
          {
            "h3": "Tôi có cần tài khoản YouTube để tải Shorts không?",
            "p": [
              "Không. Bạn chỉ cần link video Shorts để tải YouTube Shorts với CONVERT1S."
            ]
          }
        ]
      }
    ]
  }
}