{
  "seo": {
    "title": "Vimeo Downloader – Muat Turun Video HD | CONVERT1S",
    "description": "Vimeo downloader oleh CONVERT1S. Muat turun video Vimeo dalam kualiti HD secara percuma. Pantas, mudah dan tanpa pendaftaran.",
    "schemaName": "CONVERT1S - Vimeo Downloader",
    "schemaDescription": "CONVERT1S ialah pemuat turun Vimeo percuma yang membolehkan pengguna menyimpan dan memuat turun video Vimeo dalam kualiti HD dengan serta-merta.",
    "ogTitle": "Vimeo Downloader – Muat Turun Video HD | CONVERT1S",
    "ogDescription": "Muat turun video Vimeo dalam HD dengan CONVERT1S. Pemuat turun video Vimeo dalam talian yang percuma, pantas dan mudah."
  },
  "content": {
    "form": {
      "h1": "CONVERT1S – Vimeo Downloader",
      "placeholder": "Tampal URL video Vimeo di sini...",
      "button": "Muat Turun Video"
    },
    "sections": [
      {
        "h2": "Apakah CONVERT1S Vimeo Downloader?",
        "p": [
          "CONVERT1S ialah <strong>Vimeo downloader</strong> yang pantas dan percuma yang membolehkan anda menyimpan sebarang video Vimeo terus ke peranti anda dalam kualiti HD.",
          "Hanya tampal URL video Vimeo, klik muat turun, dan simpan fail video ke peranti anda tanpa memasang sebarang perisian.",
          "<strong>Pemuat turun video Vimeo</strong> ini berfungsi di semua peranti termasuk desktop, tablet dan browser mudah alih."
        ]
      },
      {
        "h2": "Cara Memuat Turun Video Vimeo",
        "ol": [
          {
            "h3": "Salin URL Video Vimeo",
            "p": [
              "Buka Vimeo dan salin pautan video yang ingin anda muat turun."
            ]
          },
          {
            "h3": "Tampal Pautan",
            "p": [
              "Tampal URL video Vimeo ke dalam CONVERT1S Vimeo downloader di atas."
            ]
          },
          {
            "h3": "Muat Turun Video",
            "p": [
              "Klik butang muat turun dan simpan video Vimeo ke peranti anda dengan serta-merta."
            ]
          }
        ]
      },
      {
        "h2": "Simpan Video Vimeo dalam Kualiti HD",
        "p": [
          "CONVERT1S memudahkan anda untuk <strong>memuat turun video Vimeo</strong> dalam HD untuk tontonan luar talian.",
          "Sama ada anda ingin menyimpan kandungan kreatif, tutorial atau video profesional dari Vimeo, alat <strong>simpan video Vimeo HD</strong> ini mengendalikannya dengan pantas dan cekap."
        ]
      },
      {
        "h2": "Mengapa Menggunakan CONVERT1S Vimeo Downloader?",
        "ul": [
          {
            "h3": "Percuma dan Tanpa Had",
            "p": [
              "Muat turun video Vimeo secara percuma tanpa had bilangan muat turun."
            ]
          },
          {
            "h3": "Muat Turun Kualiti HD",
            "p": [
              "Simpan video Vimeo dalam kualiti HD untuk pengalaman tontonan terbaik."
            ]
          },
          {
            "h3": "Tiada Pendaftaran Diperlukan",
            "p": [
              "Gunakan Vimeo downloader dengan serta-merta tanpa membuat akaun atau mendaftar."
            ]
          },
          {
            "h3": "Berfungsi di Semua Peranti",
            "p": [
              "Pemuat turun berfungsi di PC, Mac, Android, iPhone dan tablet terus dari browser."
            ]
          }
        ]
      },
      {
        "h2": "Soalan Lazim",
        "ul": [
          {
            "h3": "Adakah CONVERT1S Vimeo downloader percuma?",
            "p": [
              "Ya. CONVERT1S ialah Vimeo downloader yang sepenuhnya percuma dengan muat turun tanpa had."
            ]
          },
          {
            "h3": "Bolehkah saya memuat turun video Vimeo dalam HD?",
            "p": [
              "Ya. Anda boleh memuat turun video Vimeo dalam kualiti HD dan SD bergantung pada video sumber."
            ]
          },
          {
            "h3": "Adakah saya perlu memasang perisian?",
            "p": [
              "Tidak. Vimeo downloader berfungsi sepenuhnya dalam talian di browser anda."
            ]
          },
          {
            "h3": "Adakah ia berfungsi di peranti mudah alih?",
            "p": [
              "Ya. CONVERT1S berfungsi di Android, iPhone dan semua browser mudah alih."
            ]
          }
        ]
      }
    ]
  }
}
