{
  "seo": {
    "title": "免費無浮水印 TikTok 影片下載器線上工具 – SnackeLoader",
    "description": "使用 SnackeLoader TikTok 下載器可線上免費下載無浮水印 TikTok 影片。秒速儲存高畫質 HD TikTok 影片、相片輪播及音訊。",
    "keywords": "tiktok 下載器, 下載 tiktok 影片, 無浮水印 tiktok 下載, 線上 tiktok 影片下載, 免費下載無浮水印 tiktok 影片, 儲存高畫質無浮水印 tiktok 影片, tiktok mp4 線上下載, 無標誌 tiktok 影片儲存, 下載 tiktok 照片, 免登入 tiktok 下載, 免費無限制 tiktok 下載器, 下載高畫質 4k tiktok 影片, tiktok MP3 音訊下載",
    "schemaName": "SnackeLoader - TikTok 下載器",
    "schemaDescription": "免費的無浮水印 TikTok 影片下載器。線上免安裝、免登入快速下載高畫質 TikTok 影片、相片幻燈片及清晰音訊。",
    "ogTitle": "免費無浮水印 TikTok 影片下載器線上工具 – SnackeLoader",
    "ogDescription": "高畫質無浮水印下載 TikTok 影片。極速、免費、線上操作且免註冊免登入。"
  },
  "content": {
    "form": {
      "h1": "SnackeLoader – TikTok 下載器",
      "placeholder": "在此處貼上 TikTok 影片連結...",
      "button": "下載"
    },
    "sections": [
      {
        "h2": "什麼是 SnackeLoader TikTok 下載器？",
        "p": [
          "SnackeLoader 是一個穩定強大的 <strong>TikTok 下載器</strong>，可以協助您直接從瀏覽器<strong>無浮水印下載 TikTok 影片</strong>。",
          "只需要簡單幾個點擊，透過我們的 <strong>TikTok 影片線上下載工具</strong>，您就能輕鬆儲存高畫質影片、相片輪播圖及音訊。",
          "無須繁雜安裝、零註冊成本，更沒有令人頭疼的各種驗證與複雜步驟。"
        ]
      },
      {
        "h2": "如何下載無浮水印的 TikTok 影片",
        "ol": [
          {
            "h3": "複製 TikTok 分享連結",
            "p": [
              "開啟 TikTok 應用程式，並複製您欲儲存目標影片的 URL 連結。"
            ]
          },
          {
            "h3": "貼上神聖的 URL",
            "p": [
              "將您剛剛複製好的分享連結，貼至上方的輸入框之中。"
            ]
          },
          {
            "h3": "準備解析影片",
            "p": [
              "點擊「下載」按鈕，請給 SnackeLoader 幾秒時間以在雲端為您解析檔案。"
            ]
          },
          {
            "h3": "一鍵儲存檔案",
            "p": [
              "任意挑選您最喜歡的首選格式及畫質，即刻把 TikTok 真實影片下載到您的裝置中。"
            ]
          }
        ]
      },
      {
        "h2": "為什麼推薦使用我們的 TikTok 下載器？",
        "ul": [
          {
            "h3": "保證無浮水印",
            "p": [
              "下載沒有任何平台水印礙眼的 TikTok 原生影片文件，給您帶來最乾淨順暢的觀看和收藏體驗。"
            ]
          },
          {
            "h3": "真 HD 高畫質儲存",
            "p": [
              "能為任何儲存設備保留及下載最佳影片原始真實畫質，供日後最高品質離線播放使用。"
            ]
          },
          {
            "h3": "零時差免登入",
            "p": [
              "無需繁瑣耗時註冊建立惱人的帳戶，便可輕鬆安全體驗這個完全免費的 TikTok 萬能下載器。"
            ]
          },
          {
            "h3": "完美支援圖片與音訊萃取",
            "p": [
              "不僅限影片，將 TikTok 幻燈圖片儲存為媒體檔案，亦可在想要聆聽時進行完美的 TikTok MP3 音軌萃取。"
            ]
          }
        ]
      },
      {
        "h2": "極速順暢，並且無限制的 TikTok 儲存神隊友",
        "p": [
          "不論何時何地，我們<strong>無限制免費 TikTok 下載</strong>這項功能始終可以提供您極致且易於訪問的解析及處理服務支援。",
          "您可以在不額外加裝任何軟體的便利前提下，在 Android、iPhone、各大平板電腦與筆記本以及桌機瀏覽器完美運行。"
        ]
      },
      {
        "h2": "常見問題整理 (FAQ)",
        "ul": [
          {
            "h3": "我確定可以從這裡下載沒有無關標誌/浮水印的 TikTok 短影音嗎？",
            "p": [
              "當然沒問題。SnackeLoader 自始就是為了提供您從線上輕鬆獲取並下載無浮水印 TikTok 影片所精心開發的。"
            ]
          },
          {
            "h3": "這款 TikTok 下載器是真的全免費嗎？",
            "p": [
              "絕對是真的。這個線上工具的使用服務不收取任何費用百分百讓使用者免費到爽。"
            ]
          },
          {
            "h3": "我要下載或是安裝某個不相關的軟體或 App 嗎？",
            "p": [
              "不用。所有的功能流程一切都在您當前的常用設備瀏覽器內無縫且快速地運行解決。"
            ]
          },
          {
            "h3": "我能在行動裝置或手機系統裡面用嗎?",
            "p": [
              "肯定可以。不管是安卓手機還是蘋果 iOS，都能享有絕佳相容完美操作的線上體驗。"
            ]
          },
          {
            "h3": "每天的操作或下載次數有設定任何限制嗎？",
            "p": [
              "無任何上限！您想使用多少次，就儘管放手使用。您的日常極大需求，是工具無限大流量所樂見的。"
            ]
          }
        ]
      }
    ]
  }
}
