{
  "seo": {
    "title": "YouTubeプレイリストをダウンロード – 高速・広告なし | Y2SS",
    "description": "Y2SSでYouTubeプレイリストをオンラインでダウンロード。MP4・MP3対応、広告なし・インストール不要・無制限で利用可能。",
    "schemaName": "Y2SS YouTubeプレイリストダウンローダー",
    "schemaDescription": "ソフト不要でYouTubeプレイリストをMP4またはMP3形式で簡単にダウンロードできるオンラインツール。",
    "ogTitle": "YouTubeプレイリストダウンロード – 高速・広告なし | Y2SS",
    "ogDescription": "ワンクリックでプレイリストを保存。高速・簡単・広告なし、すべてのデバイスに対応。"
  },
  "content": {
    "form": {
      "h1": "YouTubeプレイリストダウンロード",
      "placeholder": "YouTubeプレイリストのURLを貼り付け...",
      "button": "Convert"
    },
    "sections": [
      {
        "h2": "プレイリストを一括ダウンロード",
        "p": [
          "Y2SSを使えば、YouTubeプレイリストをまとめてダウンロードできます。",
          "動画を1つずつ保存する必要はありません。URLを貼り付けるだけで一括処理が可能です。",
          "音楽、講座、ポッドキャスト、チュートリアルの保存に最適です。"
        ]
      },
      {
        "h2": "YouTubeプレイリストダウンローダーとは？",
        "p": [
          "複数の動画をまとめてダウンロードできるツールです。",
          "「YouTubeプレイリスト ダウンロード」「YouTubeプレイリスト 保存」などの検索に対応しています。",
          "Y2SSはブラウザ上で簡単に利用できます。"
        ]
      },
      {
        "h2": "ダウンロード方法",
        "p": [
          "操作は簡単で、誰でもすぐに使えます。"
        ],
        "ol": [
          {
            "h3": "URLをコピー",
            "p": [
              "YouTubeでプレイリストのURLをコピーします。"
            ]
          },
          {
            "h3": "貼り付け",
            "p": [
              "入力欄にURLを貼り付けると動画が自動検出されます。"
            ]
          },
          {
            "h3": "形式を選択",
            "p": [
              "MP4（動画）またはMP3（音声）を選びます。"
            ]
          },
          {
            "h3": "ダウンロード",
            "p": [
              "ボタンを押すとプレイリスト全体が保存されます。"
            ]
          }
        ]
      },
      {
        "h2": "MP4・MP3に対応",
        "p": [
          "動画はMP4、音声はMP3で保存できます。",
          "用途に応じて形式を選択可能です。",
          "「プレイリストをMP3に変換」「プレイリストをMP4で保存」などのニーズに対応します。"
        ]
      },
      {
        "h2": "複数動画を同時ダウンロード",
        "p": [
          "1本ずつではなく、まとめてダウンロードできます。",
          "大きなプレイリストでも効率よく保存できます。",
          "時間を大幅に節約できます。"
        ]
      },
      {
        "h2": "なぜプレイリストで保存するのか？",
        "p": [
          "個別ダウンロードは時間がかかります。",
          "多くのユーザーが一括保存を求めています。",
          "Y2SSなら一度で完了します。"
        ]
      },
      {
        "h2": "関連検索",
        "p": [
          "「YouTubeプレイリスト ダウンローダー 無料」「YouTubeプレイリスト 変換」などの検索があります。",
          "「YouTubeプレイリスト 一括ダウンロード」「プレイリスト 保存」なども人気です。",
          "Y2SSはこれらすべてに対応しています。"
        ]
      },
      {
        "h2": "音楽・講座・ポッドキャストに最適",
        "p": [
          "プレイリストはコンテンツ整理に便利です。",
          "オフラインでいつでも再生できます。",
          "学生や音楽好きにおすすめです。"
        ]
      },
      {
        "h2": "インストール不要・全デバイス対応",
        "p": [
          "ブラウザでそのまま使えます。",
          "PC・スマホ・タブレット対応。",
          "アプリ不要です。"
        ]
      },
      {
        "h2": "変換ツールとしても利用可能",
        "p": [
          "ダウンロードと同時に変換もできます。",
          "MP4・MP3に簡単に変換可能です。",
          "シンプルで使いやすい設計です。"
        ]
      },
      {
        "h2": "主な機能",
        "ul": [
          {
            "h3": "一括ダウンロード",
            "p": [
              "プレイリスト全体をまとめて保存。"
            ]
          },
          {
            "h3": "高速処理",
            "p": [
              "スムーズにダウンロード可能。"
            ]
          },
          {
            "h3": "複数形式対応",
            "p": [
              "MP4・MP3対応。"
            ]
          },
          {
            "h3": "広告なし",
            "p": [
              "快適に利用可能。"
            ]
          },
          {
            "h3": "インストール不要",
            "p": [
              "すべてオンラインで完結。"
            ]
          },
          {
            "h3": "無制限",
            "p": [
              "制限なしで利用可能。"
            ]
          }
        ]
      },
      {
        "h2": "よくある質問",
        "ul": [
          {
            "h3": "プレイリストはどうやってダウンロードしますか？",
            "p": [
              "URLをコピーして貼り付け、形式を選択してダウンロードします。"
            ]
          },
          {
            "h3": "一括ダウンロードできますか？",
            "p": [
              "はい、複数動画をまとめて保存できます。"
            ]
          },
          {
            "h3": "MP3に変換できますか？",
            "p": [
              "はい、MP3を選択してください。"
            ]
          },
          {
            "h3": "MP4対応ですか？",
            "p": [
              "はい、動画はMP4で保存できます。"
            ]
          },
          {
            "h3": "インストールは必要ですか？",
            "p": [
              "いいえ、不要です。"
            ]
          },
          {
            "h3": "無料で使えますか？",
            "p": [
              "すぐに利用できるオンラインツールです。"
            ]
          },
          {
            "h3": "スマホで使えますか？",
            "p": [
              "はい、すべてのデバイスに対応しています。"
            ]
          }
        ]
      }
    ]
  }
}