{
  "seo": {
    "title": "YouTube'dan Android'e Video İndir - Ücretsiz ve Reklamsız | YTSSS",
    "description": "YTSSS ile YouTube'dan Android'e ücretsiz video indirin. YouTube URL'sini yapıştırın ve reklamlar olmadan, kayıt olmadan, hızlı işleme ile telefonunuza anında video kaydedin.",
    "schemaName": "YTSSS - YouTube'dan Android'e Video İndir",
    "schemaDescription": "Link kullanarak YouTube videosunu Android'e indirmek için çevrimiçi araç. YouTube URL'sini yapıştırın ve reklamsız, kayıt olmadan telefonunuza anında video kaydedin.",
    "ogTitle": "YouTube'dan Android'e Video İndir - Ücretsiz ve Reklamsız | YTSSS",
    "ogDescription": "YTSSS ile link kullanarak YouTube videolarını Android'e indirin. Hızlı, ücretsiz, reklamsız ve doğrudan mobil tarayıcınızda çalışır."
  },
  "content": {
    "form": {
      "h1": "YTSSS – YouTube'dan Android'e Video İndir",
      "placeholder": "YouTube video URL'sini buraya yapıştırın...",
      "button": "Video İndir"
    },
    "sections": [
      {
        "h2": "Android İçin YTSSS YouTube İndirici Nedir?",
        "p": [
          "YTSSS, video linki kullanarak <strong>YouTube videolarını Android'e indirmenize</strong> yardımcı olan hızlı ve basit bir araçtır.",
          "URL'yi yapıştırın, videoyu işleyin ve reklamsız, kayıt olmadan doğrudan telefonunuza kaydedin.",
          "<strong>Android'de YouTube videosu indirmek</strong> için güvenilir bir yol arıyorsanız, YTSSS temiz ve verimli bir deneyim sunar."
        ]
      },
      {
        "h2": "YouTube Videosu Android'e Nasıl İndirilir",
        "ol": [
          {
            "h3": "YouTube Video Linkini Kopyalayın",
            "p": [
              "YouTube'u açın ve indirmek istediğiniz videonun URL'sini kopyalayın."
            ]
          },
          {
            "h3": "Linki YTSSS'ye Yapıştırın",
            "p": [
              "Linki sayfanın üstündeki giriş kutusuna yapıştırın."
            ]
          },
          {
            "h3": "Videoyu İşleyin",
            "p": [
              "YTSSS linki analiz eder ve Android cihazlar için indirme seçenekleri hazırlar."
            ]
          },
          {
            "h3": "Videoyu Telefonunuza İndirin",
            "p": [
              "Tercih ettiğiniz formatı veya kaliteyi seçin ve videoyu doğrudan Android cihazınıza kaydedin."
            ]
          }
        ]
      },
      {
        "h2": "Daha Fazla YouTube İndirme Aracını Keşfedin",
        "ul": [
          {
            "h3": "YouTube'dan Video İndir",
            "p": [
              "Ana indirici sayfası için <a href=\"/\"><strong>YouTube'dan Video İndir</strong></a> sayfasına gidin."
            ]
          },
          {
            "h3": "YouTube'dan Ses İndir",
            "p": [
              "Sadece ses mi gerekiyor? <a href=\"/download-audio-from-youtube\"><strong>YouTube'dan Ses İndir</strong></a> sayfasını ziyaret edin."
            ]
          },
          {
            "h3": "YouTube'dan MP4 İndir",
            "p": [
              "MP4 formatında videolar için <a href=\"/download-mp4-from-youtube\"><strong>YouTube'dan MP4 İndir</strong></a> kullanın."
            ]
          }
        ]
      },
      {
        "h2": "Android'de YouTube Videosu İndirmek İçin Neden YTSSS Kullanmalısınız?",
        "p": [
          "YTSSS, ekstra uygulama yüklemeden <strong>telefona YouTube videosu indirmek</strong> isteyen kullanıcılar için tasarlanmıştır.",
          "Araç tamamen çevrimiçi çalışır ve Android cihazlarda doğrudan video kaydetmeyi hızlı ve kolay hale getirir.",
          "<strong>Telefona YouTube videoları indirmek</strong> veya benzer mobil odaklı sorgular arayan kullanıcılar için özellikle faydalıdır."
        ]
      },
      {
        "h2": "Android'de Kolayca YouTube Videoları İndirin",
        "p": [
          "YTSSS, Android telefonlar ve tabletlerde Chrome, Firefox ve diğer mobil tarayıcılarda çalışır.",
          "Bu, yazılım yüklemeden istediğiniz zaman <strong>YouTube'dan Android'e video indirmenizi</strong> sağlar."
        ]
      },
      {
        "h2": "Hızlı ve Temiz Android İndirme Deneyimi",
        "ul": [
          {
            "h3": "Reklamsız ve Kayıt Gerektirmez",
            "p": [
              "Giriş veya reklam olmadan temiz bir deneyimin keyfini çıkarın."
            ]
          },
          {
            "h3": "Basit Link Tabanlı İndirme",
            "p": [
              "Linki yapıştırın ve anında indirin. <strong>YouTube video Android ücretsiz indir</strong> veya <strong>Android'de YouTube videosu indir</strong> arayan kullanıcılar için idealdir."
            ]
          }
        ]
      },
      {
        "h2": "Sıkça Sorulan Sorular",
        "ul": [
          {
            "h3": "YouTube videolarını Android'e nasıl indiririm?",
            "p": [
              "Video linkini kopyalayın, YTSSS'ye yapıştırın, işleyin ve videoyu telefonunuza indirin."
            ]
          },
          {
            "h3": "Video indirmek için bir uygulamaya ihtiyacım var mı?",
            "p": [
              "Hayır. YTSSS doğrudan tarayıcınızda çalışır."
            ]
          },
          {
            "h3": "Tüm Android cihazlarda çalışır mı?",
            "p": [
              "Evet. Çoğu Android telefon ve tablette çalışır."
            ]
          },
          {
            "h3": "Kayıt gerekli mi?",
            "p": [
              "Hayır. Hesap oluşturmadan aracı kullanabilirsiniz."
            ]
          },
          {
            "h3": "YTSSS YouTube ile bağlantılı mı?",
            "p": [
              "Hayır. YTSSS bağımsız bir araçtır."
            ]
          }
        ]
      }
    ]
  }
}