{
  "seo": {
    "title": "YouTube Playlist Downloader – Ganze Playlist laden | Y2SAVE",
    "description": "Laden Sie komplette YouTube Playlists online mit Y2SAVE herunter. Schneller Playlist-Downloader in hoher Qualität ohne Registrierung.",
    "schemaName": "Y2SAVE - YouTube Playlist Downloader",
    "schemaDescription": "Y2SAVE ist ein kostenloser YouTube Playlist Downloader, mit dem Nutzer ganze YouTube Playlists schnell und einfach herunterladen können.",
    "ogTitle": "YouTube Playlist Downloader – Ganze Playlist laden | Y2SAVE",
    "ogDescription": "Laden Sie ganze YouTube Playlists sofort mit Y2SAVE herunter. Kostenloser Playlist-Downloader für schnelle Massendownloads."
  },

  "content": {

    "form": {
      "h1": "YouTube Playlist Downloader",
      "placeholder": "YouTube Playlist URL hier einfügen...",
      "button": "Playlist herunterladen"
    },

    "sections": [

      {
        "h2": "Was ist ein YouTube Playlist Downloader?",
        "p": [
          "Ein <strong>YouTube Playlist Downloader</strong> ermöglicht es Ihnen, mehrere Videos aus einer Playlist in einem Vorgang herunterzuladen.",
          "Anstatt Videos einzeln herunterzuladen, können Sie einen Playlist-Link einfügen und alle Videos schnell herunterladen.",
          "Dieser <strong>Playlist-Downloader für YouTube</strong> ist ideal zum Speichern von Kursen, Tutorials, Musik-Playlists oder Videoserien für die Offline-Wiedergabe."
        ]
      },

      {
        "h2": "So laden Sie YouTube Playlist-Videos herunter",
        "ol": [
          {
            "h3": "YouTube Playlist URL kopieren",
            "p": [
              "Öffnen Sie YouTube und kopieren Sie den Link der Playlist, die Sie herunterladen möchten."
            ]
          },
          {
            "h3": "Playlist-Link einfügen",
            "p": [
              "Fügen Sie die Playlist URL in das Downloader-Tool oben ein."
            ]
          },
          {
            "h3": "Alle Videos laden",
            "p": [
              "Das Tool ruft automatisch alle Videos aus der Playlist ab."
            ]
          },
          {
            "h3": "Playlist herunterladen",
            "p": [
              "Wählen Sie Ihre bevorzugte Qualität und laden Sie die gesamte Playlist sofort herunter."
            ]
          }
        ]
      },

      {
        "h2": "Komplette YouTube Playlist einfach herunterladen",
        "p": [
          "Mit diesem Tool können Sie <strong>eine vollständige Playlist von YouTube herunterladen</strong> – mit nur wenigen Klicks.",
          "Ob Sie eine <strong>gesamte YouTube Playlist herunterladen</strong> möchten zum Offline-Lernen oder eine Videoserie speichern – der Vorgang ist schnell und einfach.",
          "Sie können auch <strong>eine ganze YouTube Playlist herunterladen</strong>, ohne Schritte zu wiederholen."
        ]
      },

      {
        "h2": "YouTube Playlist Downloader Online",
        "p": [
          "Dieser <strong>YouTube Playlist Downloader Online</strong> funktioniert direkt in Ihrem browser ohne Installation.",
          "Er ermöglicht es Ihnen, <strong>eine komplette Playlist von YouTube herunterzuladen</strong> auf jedem Gerät – Handy, Tablet oder Desktop.",
          "Sie können auch <strong>einzelne Videos aus einer YouTube Playlist herunterladen</strong>, falls gewünscht."
        ]
      },

      {
        "h2": "Warum diesen Playlist-Downloader nutzen?",
        "ul": [
          {
            "h3": "Massendownload-Unterstützung",
            "p": [
              "Laden Sie mehrere Videos auf einmal herunter, statt sie einzeln zu bearbeiten."
            ]
          },
          {
            "h3": "Schnell und einfach zu bedienen",
            "p": [
              "Fügen Sie einen Playlist-Link ein und starten Sie sofort den Download."
            ]
          },
          {
            "h3": "Funktioniert auf allen Geräten",
            "p": [
              "Kompatibel mit Android, iPhone, Tablets und Desktop-Browsern."
            ]
          }
        ]
      },

      {
        "h2": "Häufige Anwendungsfälle",
        "ul": [
          {
            "h3": "Online-Kurse herunterladen",
            "p": [
              "Speichern Sie komplette Bildungs-Playlists zum Offline-Lernen."
            ]
          },
          {
            "h3": "Musik-Playlists herunterladen",
            "p": [
              "Behalten Sie Ihre Lieblingsmusikvideos jederzeit verfügbar."
            ]
          },
          {
            "h3": "Videoserien herunterladen",
            "p": [
              "Laden Sie komplette Serien wie Tutorials, Vlogs oder Anleitungen herunter."
            ]
          }
        ]
      },

      {
        "h2": "Häufig gestellte Fragen",
        "ul": [
          {
            "h3": "Kann ich eine ganze YouTube Playlist herunterladen?",
            "p": [
              "Ja. Sie können eine gesamte Playlist von YouTube herunterladen, indem Sie den Playlist-Link in das Tool einfügen."
            ]
          },
          {
            "h3": "Ist dieser YouTube Playlist Downloader kostenlos?",
            "p": [
              "Ja. Das Tool ist komplett kostenlos ohne Einschränkungen."
            ]
          },
          {
            "h3": "Muss ich etwas installieren?",
            "p": [
              "Nein. Dies ist ein Online-Tool, das direkt in Ihrem browser funktioniert."
            ]
          },
          {
            "h3": "Kann ich es auf dem Handy nutzen?",
            "p": [
              "Ja. Es funktioniert auf allen Geräten einschließlich Android und iPhone."
            ]
          }
        ]
      }

    ]
  }
}