{
  "seo": {
    "title": "Convertidor de vídeo en línea: descarga vídeos y MP3 gratis | Convertir1s",
    "description": "Convierte y descarga vídeos de YouTube, TikTok, Facebook e Instagram con Convert1s. Conversor de vídeo online gratuito a MP4 o MP3 con descargas ilimitadas.",
    "schemaName": "Convert1s - Conversor de vídeo en línea",
    "schemaDescription": "Convert1s es un conversor y descargador de videos en línea todo en uno que permite a los usuarios descargar videos y convertirlos a MP4 o MP3 desde múltiples plataformas de redes sociales.",
    "ogTitle": "Convertidor de vídeo en línea: descarga vídeos y MP3 gratis | Convertir1s",
    "ogDescription": "Utilice el conversor de vídeo en línea Convert1s para descargar vídeos de YouTube, TikTok, Facebook e Instagram al instante."
  },
  "content": {
    "form": {
      "h1": "Convert1s – Conversor de vídeo en línea",
      "placeholder": "Pega el enlace del vídeo de YouTube, TikTok, Facebook o Instagram...",
      "button": "Convertir y descargar"
    },
    "sections": [
      {
        "h2": "¿Qué es Convert1s Online Video Converter?",
        "p": [
          "Convert1s es un potente conversor de vídeo en línea que le permite convertir vídeo a MP4 o convertir vídeo a MP3 rápidamente y descargar archivos directamente a su dispositivo.",
          "Este conversor de vídeo en línea es compatible con múltiples plataformas, incluidas YouTube, TikTok, Facebook e Instagram, para que los usuarios puedan descargar vídeos mediante un simple enlace."
        ]
      },
      {
        "h2": "Cómo convertir vídeo a MP4 o MP3",
        "ol": [
          {
            "h3": "Copia el enlace del vídeo",
            "p": [
              "Copie el enlace de YouTube, TikTok, Facebook o Instagram que desea convertir."
            ]
          },
          {
            "h3": "Pegue la URL del vídeo",
            "p": [
              "Pega el enlace en el cuadro de entrada del convertidor de vídeo en línea Convert1s."
            ]
          },
          {
            "h3": "Elija formato",
            "p": [
              "Seleccione el formato que desee, como convertir video a MP4 para video o convertir video a MP3 para audio."
            ]
          },
          {
            "h3": "Descargue el archivo convertido",
            "p": [
              "Haga clic en convertir y descargue el archivo de video o audio al instante."
            ]
          }
        ]
      },
      {
        "h2": "Descargar vídeos de plataformas populares",
        "ul": [
          {
            "h3": "Descargador de vídeos de YouTube",
            "p": [
              "Convert1s funciona como un descargador de vídeos de YouTube que te permite descargar vídeos de YouTube en línea.",
              "También puedes utilizar el conversor de YouTube a MP3 o el conversor de YouTube a MP4 para extraer audio o vídeo de cualquier enlace de YouTube."
            ]
          },
          {
            "h3": "Descargador de TikTok sin marca de agua",
            "p": [
              "Nuestro descargador de TikTok te permite descargar videos de TikTok fácilmente.",
              "Utilice el descargador de TikTok sin función de marca de agua para guardar videos sin el logotipo de TikTok."
            ]
          },
          {
            "h3": "Descargador de vídeos de Facebook",
            "p": [
              "Convert1s también funciona como un descargador de videos de Facebook que le permite descargar contenido de videos de Facebook rápidamente.",
              "Simplemente pegue el enlace para descargar videos de Facebook o reels de Facebook directamente a su dispositivo."
            ]
          },
          {
            "h3": "Descargador de vídeos de Instagram",
            "p": [
              "Descargue videos de Instagram usando nuestro descargador de videos de Instagram.",
              "También puedes guardar reels de Instagram o usar el descargador de historias de Instagram para descargar historias y reels."
            ]
          }
        ]
      },
      {
        "h2": "¿Por qué utilizar Convert1s Video Converter?",
        "ul": [
          {
            "h3": "Convertidor de vídeo en línea todo en uno",
            "p": [
              "Convert1s combina un descargador de videos y un conversor de videos en línea en una herramienta simple."
            ]
          },
          {
            "h3": "Convierte vídeo a MP4 o MP3 fácilmente",
            "p": [
              "Los usuarios pueden convertir videos a MP4 para verlos sin conexión o convertir videos a MP3 para extraer audio."
            ]
          },
          {
            "h3": "Descargas gratuitas ilimitadas",
            "p": [
              "Descarga vídeos ilimitados de YouTube, TikTok, Facebook e Instagram sin registrarte."
            ]
          },
          {
            "h3": "Funciona en todos los dispositivos",
            "p": [
              "El conversor de video en línea funciona en computadoras de escritorio, tabletas y dispositivos móviles directamente desde el navegador."
            ]
          }
        ]
      },
      {
        "h2": "Preguntas frecuentes",
        "ul": [
          {
            "h3": "¿El uso de Convert1s es gratuito?",
            "p": [
              "Sí. Convert1s es un conversor de vídeo en línea gratuito que permite descargas ilimitadas."
            ]
          },
          {
            "h3": "¿Qué plataformas son compatibles?",
            "p": [
              "El convertidor admite las funciones de descarga de vídeos de YouTube, descargador de TikTok, descargador de vídeos de Facebook y descargador de vídeos de Instagram."
            ]
          },
          {
            "h3": "¿Puedo convertir vídeo a MP3?",
            "p": [
              "Sí. La herramienta incluye un conversor de YouTube a MP3 y te permite convertir vídeos a MP3 fácilmente."
            ]
          }
        ]
      }
    ]
  }
}