{
  "seo": {
    "title": "Vimeo Downloader – Muat Turun Video HD | SNAP1S",
    "description": "Muat turun video Vimeo dalam kualiti HD dengan SNAP1S. Pemuat turun video Vimeo percuma yang menyimpan video terus ke peranti anda. Tanpa pendaftaran atau app.",
    "schemaName": "SNAP1S - Pemuat Turun Video Vimeo",
    "schemaDescription": "SNAP1S ialah pemuat turun video Vimeo percuma yang membolehkan pengguna memuat turun video Vimeo dalam kualiti HD terus ke mana-mana peranti.",
    "ogTitle": "Vimeo Downloader – Muat Turun Video HD | SNAP1S",
    "ogDescription": "Muat turun video Vimeo dalam HD dengan SNAP1S. Percuma, pantas dan berkualiti tinggi."
  },
  "content": {
    "form": {
      "h1": "SNAP1S – Pemuat Turun Video Vimeo",
      "placeholder": "Tampal URL video Vimeo di sini...",
      "button": "Muat Turun Video"
    },
    "sections": [
      {
        "h2": "Apa Itu SNAP1S Vimeo Downloader?",
        "p": [
          "SNAP1S ialah <strong>Vimeo downloader</strong> percuma yang membolehkan anda menyimpan video Vimeo terus ke telefon, tablet, atau komputer dalam kualiti HD.",
          "Hanya tampal pautan video Vimeo, klik muat turun, dan video akan disimpan ke peranti anda dalam beberapa saat.",
          "<strong>Pemuat turun video Vimeo</strong> ini berfungsi pada semua peranti dan browser tanpa perlu memasang app atau membuat akaun."
        ]
      },
      {
        "h2": "Cara Memuat Turun Video Vimeo",
        "ol": [
          {
            "h3": "Salin Pautan Video Vimeo",
            "p": [
              "Buka Vimeo dan salin URL video yang ingin dimuat turun dari bar alamat atau butang kongsi."
            ]
          },
          {
            "h3": "Tampal Pautan",
            "p": [
              "Tampal URL video Vimeo ke pemuat turun SNAP1S Vimeo di atas."
            ]
          },
          {
            "h3": "Muat Turun Video",
            "p": [
              "Klik butang muat turun dan simpan video Vimeo dalam kualiti HD ke peranti anda."
            ]
          }
        ]
      },
      {
        "h2": "Simpan Video Vimeo dalam Kualiti HD",
        "p": [
          "SNAP1S membolehkan anda <strong>memuat turun video Vimeo</strong> dalam resolusi tertinggi yang tersedia, termasuk 720p, 1080p, dan juga 4K jika tersedia.",
          "Nikmati kandungan Vimeo kegemaran anda secara luar talian — sama ada filem, tutorial, video muzik, atau projek kreatif."
        ]
      },
      {
        "h2": "Mengapa Menggunakan SNAP1S Vimeo Downloader?",
        "ul": [
          {
            "h3": "Muat Turun Kualiti HD",
            "p": [
              "Muat turun video Vimeo dalam resolusi Full HD atau 4K untuk menikmati pengalaman tontonan luar talian yang terbaik."
            ]
          },
          {
            "h3": "Pantas dan Mudah",
            "p": [
              "Hanya tampal pautan dan klik muat turun. Proses <strong>simpan video Vimeo HD</strong> hanya mengambil beberapa saat."
            ]
          },
          {
            "h3": "Percuma dan Tanpa Had",
            "p": [
              "Muat turun seberapa banyak video Vimeo yang anda mahu secara percuma tanpa had harian atau caj tersembunyi."
            ]
          },
          {
            "h3": "Tanpa App",
            "p": [
              "<strong>Pemuat turun video Vimeo</strong> berfungsi terus dalam browser anda pada mana-mana peranti tanpa memasang app."
            ]
          }
        ]
      },
      {
        "h2": "Soalan Lazim",
        "ul": [
          {
            "h3": "Adakah SNAP1S Vimeo downloader percuma?",
            "p": [
              "Ya. SNAP1S ialah pemuat turun Vimeo yang sepenuhnya percuma tanpa caj tersembunyi atau langganan."
            ]
          },
          {
            "h3": "Bolehkah saya memuat turun video Vimeo dalam HD?",
            "p": [
              "Ya. SNAP1S menyokong muat turun video Vimeo dalam kualiti HD, Full HD, dan 4K jika tersedia."
            ]
          },
          {
            "h3": "Adakah ia berfungsi pada iPhone dan Android?",
            "p": [
              "Ya. Pemuat turun Vimeo berfungsi pada semua peranti mudah alih dan browser desktop."
            ]
          },
          {
            "h3": "Perlukah akaun Vimeo untuk memuat turun?",
            "p": [
              "Tidak. Anda hanya perlukan pautan video untuk memuat turun video Vimeo dengan SNAP1S."
            ]
          }
        ]
      }
    ]
  }
}