{
  "seo": {
    "title": "YouTube অডিও অনলাইনে বিনামূল্যে সেভ করুন - বিজ্ঞাপন নেই | SSTube",
    "description": "SSTube দিয়ে YouTube ভিডিও থেকে অনলাইনে অডিও সেভ করুন। বিজ্ঞাপন ছাড়া, রেজিস্ট্রেশন ছাড়া দ্রুত অডিও এক্সট্র্যাক্ট করুন যেকোনো ডিভাইসে।",
    "schemaName": "SSTube - YouTube অডিও সেভ করুন",
    "schemaDescription": "YouTube ভিডিও থেকে তাৎক্ষণিকভাবে অডিও সেভ করার অনলাইন টুল। YouTube লিংক পেস্ট করুন এবং বিজ্ঞাপন ও রেজিস্ট্রেশন ছাড়া অডিও এক্সট্র্যাক্ট করুন।",
    "ogTitle": "YouTube অডিও অনলাইনে বিনামূল্যে সেভ করুন - বিজ্ঞাপন নেই | SSTube",
    "ogDescription": "SSTube দিয়ে YouTube ভিডিও থেকে তাৎক্ষণিকভাবে অডিও এক্সট্র্যাক্ট ও সেভ করুন। দ্রুত, বিনামূল্যে এবং সব ডিভাইসে কাজ করে।"
  },
  "content": {
    "form": {
      "h1": "SSTube – YouTube অডিও সেভ করুন",
      "placeholder": "এখানে YouTube ভিডিও URL পেস্ট করুন...",
      "button": "অডিও সেভ করুন"
    },
    "sections": [
      {
        "h2": "SSTube YouTube অডিও সেভ টুল কী?",
        "p": [
          "SSTube হলো একটি সহজ এবং কার্যকর <strong>YouTube অডিও সেভ</strong> টুল যা ব্যবহারকারীদের ব্রাউজার থেকে সরাসরি YouTube ভিডিও থেকে অডিও এক্সট্র্যাক্ট ও সেভ করতে দেয়।",
          "আপনি যদি সফটওয়্যার ইনস্টল না করে বা জটিল টুল ব্যবহার না করে <strong>YouTube থেকে অডিও সেভ</strong> করতে চান, SSTube একটি পরিষ্কার, দ্রুত এবং বিজ্ঞাপনমুক্ত সমাধান প্রদান করে।",
          "শুধু ভিডিও URL পেস্ট করুন, লিংক প্রসেস করুন এবং যেকোনো ডিভাইসে তাৎক্ষণিকভাবে অডিও সেভ করুন।"
        ]
      },
      {
        "h2": "YouTube থেকে অডিও কীভাবে সেভ করবেন",
        "ol": [
          {
            "h3": "YouTube ভিডিও URL কপি করুন",
            "p": [
              "YouTube খুলুন এবং যে ভিডিও থেকে অডিও এক্সট্র্যাক্ট করতে চান তার লিংক কপি করুন।"
            ]
          },
          {
            "h3": "SSTube-এ URL পেস্ট করুন",
            "p": [
              "উপরের ইনপুট বক্সে ভিডিও লিংক পেস্ট করুন।"
            ]
          },
          {
            "h3": "অডিও প্রসেস করুন",
            "p": [
              "SSTube লিংক পড়ে এবং দ্রুত অডিও এক্সট্র্যাকশন প্রস্তুত করে।"
            ]
          },
          {
            "h3": "অডিও ফাইল সেভ করুন",
            "p": [
              "আপনার পছন্দের আউটপুট বেছে নিন এবং তাৎক্ষণিকভাবে অডিও ফাইল সেভ করুন।"
            ]
          }
        ]
      },
      {
        "h2": "আরও YouTube সেভ টুল অন্বেষণ করুন",
        "ul": [
          {
            "h3": "সম্পূর্ণ YouTube ভিডিও সেভ করুন",
            "p": [
              "একই সহজ প্রক্রিয়ায় সম্পূর্ণ ভিডিও সেভ করতে <a href=\"/\"><strong>YouTube ভিডিও সেভ</strong></a> ব্যবহার করুন।"
            ]
          },
          {
            "h3": "YouTube Shorts সেভ করুন",
            "p": [
              "শর্ট ভিডিও দরকার? দ্রুত Shorts সেভ করতে <a href=\"/save-youtube-shorts\"><strong>YouTube Shorts সেভ</strong></a> দেখুন।"
            ]
          },
          {
            "h3": "HD বা 4K ভিডিও সেভ করুন",
            "p": [
              "উচ্চ মানের ভিডিও আউটপুটের জন্য, <a href=\"/save-youtube-video-hd\"><strong>YouTube ভিডিও HD সেভ</strong></a>-এ যান।"
            ]
          }
        ]
      },
      {
        "h2": "YouTube অডিও সেভ করতে কেন SSTube ব্যবহার করবেন?",
        "p": [
          "SSTube সরলতা এবং গতির উপর ফোকাস করে। ব্যবহারকারীরা <strong>youtube অডিও সেভ</strong>, <strong>youtube থেকে mp3</strong>, বা <strong>youtube অডিও ডাউনলোডার</strong> যাই খুঁজুক না কেন, এই পৃষ্ঠাটি সেই চাহিদা পূরণ করে এবং ব্র্যান্ডকে <strong>সেভ</strong> শব্দের উপর কেন্দ্রীভূত রাখে।",
          "টুলটি সম্পূর্ণ অনলাইনে কাজ করে এবং জটিল কনভার্টার বা ভারী ডেস্কটপ সফটওয়্যারের প্রয়োজনীয়তা দূর করে।"
        ]
      },
      {
        "h2": "যেকোনো ডিভাইসে অডিও সেভ করুন",
        "p": [
          "আপনি ডেস্কটপ কম্পিউটার, ল্যাপটপ, ট্যাবলেট, অ্যান্ড্রয়েড ফোন এবং আইফোনে SSTube ব্যবহার করতে পারেন।",
          "এটি অ্যাপ ইনস্টল বা ডিভাইস পরিবর্তন না করে অনলাইনে YouTube অডিও সেভ করা সহজ করে।"
        ]
      },
      {
        "h2": "দ্রুত এবং পরিষ্কার অডিও সেভিং অভিজ্ঞতা",
        "ul": [
          {
            "h3": "কোনো বিজ্ঞাপন নেই এবং রেজিস্ট্রেশন নেই",
            "p": [
              "পপআপ, বিজ্ঞাপন বা অ্যাকাউন্টের প্রয়োজনীয়তা ছাড়া একটি পরিষ্কার ইন্টারফেস উপভোগ করুন।"
            ]
          },
          {
            "h3": "সহজ লিংক-ভিত্তিক ওয়ার্কফ্লো",
            "p": [
              "লিংক পেস্ট করুন এবং তাৎক্ষণিকভাবে প্রসেস করুন। এটি <strong>youtube ভিডিও থেকে অডিও ডাউনলোড</strong> এবং <strong>youtube ভিডিও থেকে গান ডাউনলোড</strong> এর মতো সার্চের সাথে সামঞ্জস্যপূর্ণ।"
            ]
          },
          {
            "h3": "অডিও এক্সট্র্যাকশনের জন্য অপ্টিমাইজড",
            "p": [
              "SSTube বিশেষভাবে প্রক্রিয়াকে ন্যূনতম রেখে দক্ষতার সাথে অডিও এক্সট্র্যাক্ট করার জন্য ডিজাইন করা হয়েছে।"
            ]
          }
        ]
      },
      {
        "h2": "YouTube অডিও সেভিং বনাম অন্যান্য পদ্ধতি",
        "ul": [
          {
            "h3": "ইনস্টলেশন ছাড়া অনলাইন টুল",
            "p": [
              "প্রচলিত কনভার্টারের বিপরীতে, SSTube সরাসরি আপনার ব্রাউজারে কাজ করে।"
            ]
          },
          {
            "h3": "অনেক কনভার্টারের চেয়ে দ্রুত",
            "p": [
              "সুবিন্যস্ত ইন্টারফেস ব্যবহারকারীদের অনেক ভারী টুলের চেয়ে দ্রুত অডিও প্রসেস ও সেভ করতে সাহায্য করে।"
            ]
          }
        ]
      },
      {
        "h2": "সচরাচর জিজ্ঞাসিত প্রশ্নাবলী",
        "ul": [
          {
            "h3": "YouTube থেকে কীভাবে অডিও সেভ করব?",
            "p": [
              "YouTube URL কপি করুন, SSTube-এ পেস্ট করুন, লিংক প্রসেস করুন এবং অডিও ফাইল সেভ করুন।"
            ]
          },
          {
            "h3": "সফটওয়্যার ইনস্টল করতে হবে?",
            "p": [
              "না। SSTube সম্পূর্ণ অনলাইনে আপনার ব্রাউজারে কাজ করে।"
            ]
          },
          {
            "h3": "মোবাইলে SSTube ব্যবহার করা যাবে?",
            "p": [
              "হ্যাঁ। এটি অ্যান্ড্রয়েড, আইফোন এবং ট্যাবলেটে কাজ করে।"
            ]
          },
          {
            "h3": "SSTube কি বিনামূল্যে?",
            "p": [
              "হ্যাঁ। আপনি কোনো পেমেন্ট বা রেজিস্ট্রেশন ছাড়াই টুলটি ব্যবহার করতে পারেন।"
            ]
          },
          {
            "h3": "SSTube কি YouTube-এর সাথে যুক্ত?",
            "p": [
              "না। SSTube একটি স্বতন্ত্র টুল।"
            ]
          }
        ]
      }
    ]
  }
}