{
  "seo": {
    "title": "YouTube ऑडियो ऑनलाइन मुफ्त सेव करें - बिना विज्ञापन | SSTube",
    "description": "SSTube के साथ YouTube वीडियो से ऑनलाइन ऑडियो सेव करें। बिना विज्ञापन, बिना रजिस्ट्रेशन, किसी भी डिवाइस पर तेज़ प्रोसेसिंग के साथ जल्दी ऑडियो एक्सट्रैक्ट करें।",
    "schemaName": "SSTube - YouTube ऑडियो सेव करें",
    "schemaDescription": "YouTube वीडियो से तुरंत ऑडियो सेव करने का ऑनलाइन टूल। YouTube लिंक पेस्ट करें और बिना विज्ञापन और बिना रजिस्ट्रेशन के ऑडियो एक्सट्रैक्ट करें।",
    "ogTitle": "YouTube ऑडियो ऑनलाइन मुफ्त सेव करें - बिना विज्ञापन | SSTube",
    "ogDescription": "SSTube के साथ YouTube वीडियो से तुरंत ऑडियो एक्सट्रैक्ट और सेव करें। तेज़, मुफ्त और सभी डिवाइस पर काम करता है।"
  },
  "content": {
    "form": {
      "h1": "SSTube – YouTube ऑडियो सेव करें",
      "placeholder": "YouTube वीडियो URL यहाँ पेस्ट करें...",
      "button": "ऑडियो सेव करें"
    },
    "sections": [
      {
        "h2": "SSTube YouTube ऑडियो सेव टूल क्या है?",
        "p": [
          "SSTube एक सरल और कुशल <strong>YouTube ऑडियो सेव</strong> टूल है जो उपयोगकर्ताओं को ब्राउज़र से सीधे YouTube वीडियो से ऑडियो एक्सट्रैक्ट और सेव करने की अनुमति देता है।",
          "यदि आप सॉफ्टवेयर इंस्टॉल किए बिना या जटिल टूल्स का उपयोग किए बिना <strong>YouTube से ऑडियो सेव</strong> करना चाहते हैं, तो SSTube एक साफ, तेज़ और विज्ञापन-मुक्त समाधान प्रदान करता है।",
          "बस वीडियो URL पेस्ट करें, लिंक प्रोसेस करें और किसी भी डिवाइस पर तुरंत ऑडियो सेव करें।"
        ]
      },
      {
        "h2": "YouTube से ऑडियो कैसे सेव करें",
        "ol": [
          {
            "h3": "YouTube वीडियो URL कॉपी करें",
            "p": [
              "YouTube खोलें और उस वीडियो का लिंक कॉपी करें जिससे आप ऑडियो एक्सट्रैक्ट करना चाहते हैं।"
            ]
          },
          {
            "h3": "SSTube में URL पेस्ट करें",
            "p": [
              "ऊपर दिए गए इनपुट बॉक्स में वीडियो लिंक पेस्ट करें।"
            ]
          },
          {
            "h3": "ऑडियो प्रोसेस करें",
            "p": [
              "SSTube लिंक पढ़ता है और जल्दी से ऑडियो एक्सट्रैक्शन तैयार करता है।"
            ]
          },
          {
            "h3": "ऑडियो फ़ाइल सेव करें",
            "p": [
              "अपना पसंदीदा आउटपुट चुनें और तुरंत ऑडियो फ़ाइल सेव करें।"
            ]
          }
        ]
      },
      {
        "h2": "और YouTube सेव टूल्स खोजें",
        "ul": [
          {
            "h3": "पूर्ण YouTube वीडियो सेव करें",
            "p": [
              "उसी सरल प्रक्रिया से पूर्ण वीडियो सेव करने के लिए <a href=\"/\"><strong>YouTube वीडियो सेव</strong></a> का उपयोग करें।"
            ]
          },
          {
            "h3": "YouTube Shorts सेव करें",
            "p": [
              "शॉर्ट वीडियो चाहिए? तेज़ Shorts सेविंग के लिए <a href=\"/save-youtube-shorts\"><strong>YouTube Shorts सेव</strong></a> पर जाएँ।"
            ]
          },
          {
            "h3": "HD या 4K वीडियो सेव करें",
            "p": [
              "उच्च गुणवत्ता वाले वीडियो आउटपुट के लिए, <a href=\"/save-youtube-video-hd\"><strong>YouTube वीडियो HD सेव</strong></a> पर जाएँ।"
            ]
          }
        ]
      },
      {
        "h2": "YouTube ऑडियो सेव करने के लिए SSTube क्यों उपयोग करें?",
        "p": [
          "SSTube सरलता और गति पर केंद्रित है। चाहे उपयोगकर्ता <strong>youtube ऑडियो सेव</strong>, <strong>youtube to mp3</strong>, या <strong>youtube ऑडियो डाउनलोडर</strong> खोजें, यह पेज उस इरादे से मेल खाता है और ब्रांड को <strong>सेव</strong> शब्द पर केंद्रित रखता है।",
          "यह टूल पूरी तरह से ऑनलाइन काम करता है और जटिल कन्वर्टर्स या भारी डेस्कटॉप सॉफ्टवेयर की आवश्यकता को समाप्त करता है।"
        ]
      },
      {
        "h2": "किसी भी डिवाइस पर ऑडियो सेव करें",
        "p": [
          "आप डेस्कटॉप कंप्यूटर, लैपटॉप, टैबलेट, Android फोन और iPhone पर SSTube का उपयोग कर सकते हैं।",
          "इससे ऐप्स इंस्टॉल किए बिना या डिवाइस बदले बिना ऑनलाइन YouTube ऑडियो सेव करना आसान हो जाता है।"
        ]
      },
      {
        "h2": "तेज़ और साफ ऑडियो सेविंग अनुभव",
        "ul": [
          {
            "h3": "कोई विज्ञापन नहीं और कोई रजिस्ट्रेशन नहीं",
            "p": [
              "पॉपअप, विज्ञापन या अकाउंट आवश्यकताओं के बिना एक साफ इंटरफ़ेस का आनंद लें।"
            ]
          },
          {
            "h3": "सरल लिंक-आधारित वर्कफ़्लो",
            "p": [
              "लिंक पेस्ट करें और तुरंत प्रोसेस करें। यह <strong>youtube वीडियो से ऑडियो डाउनलोड</strong> और <strong>youtube वीडियो से गाना डाउनलोड</strong> जैसी खोजों से मेल खाता है।"
            ]
          },
          {
            "h3": "ऑडियो एक्सट्रैक्शन के लिए ऑप्टिमाइज़्ड",
            "p": [
              "SSTube विशेष रूप से प्रक्रिया को न्यूनतम रखते हुए कुशलता से ऑडियो एक्सट्रैक्ट करने के लिए डिज़ाइन किया गया है।"
            ]
          }
        ]
      },
      {
        "h2": "YouTube ऑडियो सेविंग बनाम अन्य तरीके",
        "ul": [
          {
            "h3": "बिना इंस्टॉलेशन के ऑनलाइन टूल",
            "p": [
              "पारंपरिक कन्वर्टर्स के विपरीत, SSTube सीधे आपके ब्राउज़र में काम करता है।"
            ]
          },
          {
            "h3": "कई कन्वर्टर्स से तेज़",
            "p": [
              "सुव्यवस्थित इंटरफ़ेस उपयोगकर्ताओं को कई भारी टूल्स की तुलना में तेज़ी से ऑडियो प्रोसेस और सेव करने में मदद करता है।"
            ]
          }
        ]
      },
      {
        "h2": "अक्सर पूछे जाने वाले प्रश्न",
        "ul": [
          {
            "h3": "YouTube से ऑडियो कैसे सेव करें?",
            "p": [
              "YouTube URL कॉपी करें, SSTube में पेस्ट करें, लिंक प्रोसेस करें और ऑडियो फ़ाइल सेव करें।"
            ]
          },
          {
            "h3": "क्या मुझे सॉफ्टवेयर इंस्टॉल करना होगा?",
            "p": [
              "नहीं। SSTube पूरी तरह से आपके ब्राउज़र में ऑनलाइन काम करता है।"
            ]
          },
          {
            "h3": "क्या मैं मोबाइल पर SSTube का उपयोग कर सकता हूँ?",
            "p": [
              "हाँ। यह Android, iPhone और टैबलेट पर काम करता है।"
            ]
          },
          {
            "h3": "क्या SSTube मुफ्त है?",
            "p": [
              "हाँ। आप बिना भुगतान या रजिस्ट्रेशन के टूल का उपयोग कर सकते हैं।"
            ]
          },
          {
            "h3": "क्या SSTube YouTube से संबद्ध है?",
            "p": [
              "नहीं। SSTube एक स्वतंत्र टूल है।"
            ]
          }
        ]
      }
    ]
  }
}